[
  {
    "productId": 1,
    "price": "23400",
    "brandId": 1,
    "title": "베이지 텍스처 셔츠",
    "wishYN": "N",
    "imgUrls": [
      "https://img1.shopcider.com/product/1632651869000-kwhNwZ.jpg?x-oss-process=image/resize,w_350,m_lfit/quality,Q_80/interlace,1",
      "https://img.shopcider.com/hermes/video/1673859643000-6grjzb.jpg?x-oss-process=image/resize,w_350,m_lfit/quality,Q_80/interlace,1"
    ],
    "href": ""
  },
  {
    "productId": 4,
    "price": "26000",
    "brandId": 1,
    "title": "캣츠 프린팅 탑셔츠",
    "wishYN": "N",
    "imgUrls": [
      "https://img1.shopcider.com/product/1623205683000-NHARCR.jpg?x-oss-process=image/resize,w_350,m_lfit/quality,Q_80/interlace,1",
      "https://img1.shopcider.com/product/1623205683000-kDXFbE.jpg?x-oss-process=image/resize,w_350,m_lfit/quality,Q_80/interlace,1"
    ],
    "href": ""
  },
  {
    "productId": 3,
    "price": "28600",
    "brandId": 1,
    "title": "플로럴 레이스 미니 원피스",
    "wishYN": "N",
    "imgUrls": [
      "https://img1.shopcider.com/product/1660794981000-rMWbHf.jpg?x-oss-process=image/resize,w_350,m_lfit/quality,Q_80/interlace,1",
      "https://img1.shopcider.com/product/1660649142000-TD6HZw.jpg?x-oss-process=image/resize,w_350,m_lfit/quality,Q_80/interlace,1"
    ],
    "href": ""
  },
  {
    "productId": 4,
    "price": "20800",
    "brandId": 1,
    "title": "버튼업 반팔 크롭 후드탑",
    "wishYN": "N",
    "imgUrls": [
      "https://img1.shopcider.com/product/1679318783000-cPaQMb.jpg?x-oss-process=image/resize,w_350,m_lfit/quality,Q_80/interlace,1",
      "https://img1.shopcider.com/product/1679318783000-Xh5N2J.jpg?x-oss-process=image/resize,w_350,m_lfit/quality,Q_80/interlace,1"
    ],
    "href": ""
  },
  {
    "productId": 5,
    "price": "28600",
    "brandId": 1,
    "title": "카라 버튼 다운 블라우스",
    "wishYN": "N",
    "imgUrls": [
      "https://img1.shopcider.com/product/1659755930000-2zwJic.jpg?x-oss-process=image/resize,w_350,m_lfit/quality,Q_80/interlace,1",
      "https://img1.shopcider.com/product/1659755930000-MiM5yD.jpg?x-oss-process=image/resize,w_350,m_lfit/quality,Q_80/interlace,1"
    ],
    "href": ""
  },
  {
    "productId": 6,
    "price": "26000",
    "brandId": 1,
    "title": "솔리드 텍스처 칼라 크롭 탑",
    "wishYN": "N",
    "imgUrls": [
      "https://img1.shopcider.com/product/1648628969000-KfCtWT.jpg?x-oss-process=image/resize,w_350,m_lfit/quality,Q_80/interlace,1",
      "https://img.shopcider.com/hermes/video/1689833562000-2kxaca.jpg?x-oss-process=image/resize,w_350,m_lfit/quality,Q_80/interlace,1"
    ],
    "href": ""
  },
  {
    "productId": 7,
    "price": "18200",
    "brandId": 1,
    "title": "Keep Rolling 그래픽 크롭 탑",
    "wishYN": "N",
    "imgUrls": [
      "https://img1.shopcider.com/product/1658730470000-DycYZ2.jpg?x-oss-process=image/resize,w_350,m_lfit/quality,Q_80/interlace,1",
      "https://img1.shopcider.com/product/1659419253000-bTdmp8.jpg?x-oss-process=image/resize,w_350,m_lfit/quality,Q_80/interlace,1"
    ],
    "href": ""
  },
  {
    "productId": 8,
    "price": "13200",
    "brandId": 1,
    "title": "버클 U넥 반팔탑",
    "wishYN": "N",
    "imgUrls": [
      "https://img1.shopcider.com/product/1680947912000-EdNB5z.jpg?x-oss-process=image/resize,w_350,m_lfit/quality,Q_80/interlace,1",
      "https://img1.shopcider.com/product/1680947912000-DWrw2T.jpg?x-oss-process=image/resize,w_350,m_lfit/quality,Q_80/interlace,1"
    ],
    "href": ""
  },
  {
    "productId": 9,
    "price": "26000",
    "brandId": 1,
    "title": "솔리드 미들 웨이스트 플리츠 스커트",
    "wishYN": "N",
    "imgUrls": [
      "https://img1.shopcider.com/product/1672226822000-wKRSMp.jpg?x-oss-process=image/resize,w_350,m_lfit/quality,Q_80/interlace,1",
      "https://img.shopcider.com/hermes/video/1680506294000-7jq6dz.jpg?x-oss-process=image/resize,w_350,m_lfit/quality,Q_80/interlace,1"
    ],
    "href": ""
  },
  {
    "productId": 10,
    "price": "22800",
    "brandId": 1,
    "title": "저지 플라워 그래픽 반팔 탑셔츠",
    "wishYN": "N",
    "imgUrls": [
      "https://img1.shopcider.com/product/1675236673000-8yinH6.jpg?x-oss-process=image/resize,w_350,m_lfit/quality,Q_80/interlace,1",
      "https://img1.shopcider.com/product/1675236673000-JZwbJf.jpg?x-oss-process=image/resize,w_350,m_lfit/quality,Q_80/interlace,1"
    ],
    "href": ""
  },
  {
    "productId": 11,
    "price": "15800",
    "brandId": 1,
    "title": "메쉬 카울넥 크롭 캐미탑",
    "wishYN": "N",
    "imgUrls": [
      "https://img1.shopcider.com/product/1671592312000-jiEfnB.jpg?x-oss-process=image/resize,w_350,m_lfit/quality,Q_80/interlace,1",
      "https://img1.shopcider.com/product/1671592312000-TWxHZA.jpg?x-oss-process=image/resize,w_350,m_lfit/quality,Q_80/interlace,1"
    ],
    "href": ""
  },
  {
    "productId": 12,
    "price": "5300",
    "brandId": 1,
    "title": "지오디자인 후프 이어링",
    "wishYN": "N",
    "imgUrls": [
      "https://img1.shopcider.com/product/1654850709000-rjHC7C.jpg?x-oss-process=image/resize,w_350,m_lfit/quality,Q_80/interlace,1",
      "https://img1.shopcider.com/product/1654850712000-5XAdsE.jpg?x-oss-process=image/resize,w_350,m_lfit/quality,Q_80/interlace,1"
    ],
    "href": ""
  },
  {
    "productId": 13,
    "price": "10500",
    "brandId": 1,
    "title": "솔리드 홀터넥 매듭 캐미 크롭 탑",
    "wishYN": "N",
    "imgUrls": [
      "https://img1.shopcider.com/product/1671287284000-DwfCx6.jpg?x-oss-process=image/resize,w_350,m_lfit/quality,Q_80/interlace,1",
      "https://img1.shopcider.com/product/1671287284000-Yi7hKF.jpg?x-oss-process=image/resize,w_350,m_lfit/quality,Q_80/interlace,1"
    ],
    "href": ""
  },
  {
    "productId": 14,
    "price": "39600",
    "brandId": 1,
    "title": "Miss Crafty 패치워크 데님 미디 스커트",
    "wishYN": "N",
    "imgUrls": [
      "https://img1.shopcider.com/product/1661430337000-KWsGjJ.jpg?x-oss-process=image/resize,w_350,m_lfit/quality,Q_80/interlace,1",
      "https://img.shopcider.com/hermes/video/1674191970000-3rydss.jpg?x-oss-process=image/resize,w_350,m_lfit/quality,Q_80/interlace,1"
    ],
    "href": ""
  },
  {
    "productId": 15,
    "price": "33800",
    "brandId": 1,
    "title": "Ditsy 플로럴 타이 숄더 미니 원피스",
    "wishYN": "N",
    "imgUrls": [
      "https://img1.shopcider.com/product/1654573339000-SphSXT.jpg?x-oss-process=image/resize,w_350,m_lfit/quality,Q_80/interlace,1",
      "https://img1.shopcider.com/product/1654573339000-aeRSX8.jpg?x-oss-process=image/resize,w_350,m_lfit/quality,Q_80/interlace,1"
    ],
    "href": ""
  },
  {
    "productId": 16,
    "price": "26100",
    "brandId": 1,
    "title": "데님 솔리드 하이웨이스트 미니스커트",
    "wishYN": "N",
    "imgUrls": [
      "https://img1.shopcider.com/product/1665975823000-W3cJnJ.jpg?x-oss-process=image/resize,w_350,m_lfit/quality,Q_80/interlace,1",
      "https://img1.shopcider.com/product/1671517731000-hNt4Je.jpg?x-oss-process=image/resize,w_350,m_lfit/quality,Q_80/interlace,1"
    ],
    "href": ""
  },
  {
    "productId": 17,
    "price": "29000",
    "brandId": 1,
    "title": "플리츠 레이스업 미니스커트",
    "wishYN": "N",
    "imgUrls": [
      "https://img1.shopcider.com/product/1680860694000-hFeszx.jpg?x-oss-process=image/resize,w_350,m_lfit/quality,Q_80/interlace,1",
      "https://img1.shopcider.com/product/1680785625000-wPK8ZN.jpg?x-oss-process=image/resize,w_350,m_lfit/quality,Q_80/interlace,1"
    ],
    "href": ""
  },
  {
    "productId": 18,
    "price": "28600",
    "brandId": 1,
    "title": "래빗 니트 크롭 탱크탑",
    "wishYN": "N",
    "imgUrls": [
      "https://img1.shopcider.com/product/1681902980000-QG2Q8W.jpg?x-oss-process=image/resize,w_350,m_lfit/quality,Q_80/interlace,1",
      "https://img1.shopcider.com/product/1679020183000-BjP5BP.jpg?x-oss-process=image/resize,w_350,m_lfit/quality,Q_80/interlace,1"
    ],
    "href": "https://www.shopcider.com/goods/rabbit-knit-crop-tank-top-1033939?style_id=137855&gaListId=-----1&gaListName=%25EC%2583%25B5%25EC%2582%25AC%25EC%259D%25B4%25EB%258B%25A4%2520%25EC%2584%259C%25EC%259A%25B8%2520%25ED%258C%259D%25EC%2597%2585%2520%25EC%258A%25A4%25ED%2586%25A0%25EC%2596%25B4%2520%25EC%25BB%25AC%25EB%25A0%2589%25EC%2585%2598&ciderListId=2&ciderListName=%EC%83%B5%EC%82%AC%EC%9D%B4%EB%8B%A4%20%EC%84%9C%EC%9A%B8%20%ED%8C%9D%EC%97%85%20%EC%8A%A4%ED%86%A0%EC%96%B4%20%EC%BB%AC%EB%A0%89%EC%85%98&selectSkuIndex=0&moduleTitle=1&p=1033939&shopPage=7&shopIndex=123&navTitle=%25EC%2583%25B5%25EC%2582%25AC%25EC%259D%25B4%25EB%258B%25A4%2520%25EC%2584%259C%25EC%259A%25B8%2520%25ED%258C%259D%25EC%2597%2585%2520%25EC%258A%25A4%25ED%2586%25A0%25EC%2596%25B4%2520%25EC%25BB%25AC%25EB%25A0%2589%25EC%2585%2598&navId=-----1&listSort=&listId=11121&listAttribute=&operationContent=&operationImage=&linkUrl=&operationpageTitle=&operationPosition=&operationType=&productPosition=124&strategyNameList=&businessTracking=eyJmaXJzdEltYWdlVHlwZSI6Iuato%2BmdouS4iuWNiui6qyIsIml0ZW1UeXBlIjowLCJsaXN0SWQiOjExMTIxLCJsaXN0VGl0bGUiOiLsg7XsgqzsnbTri6Qg7ISc7Jq4IO2MneyXhSDsiqTthqDslrQg7Lus66CJ7IWYIiwibGlzdFR5cGUiOjIsIm1vZHVsZUlkIjoxLCJwcm9kdWN0UHJpbWFyeUltYWdlRmxhZyI6dHJ1ZSwic2FsZVByaWNlIjoyMy4wMCwic2tjRmlyc3RJbWciOiIxNjgxOTAyOTgwMDAwLVFHMlE4Vy5qcGciLCJzcHUiOjEwMzM5MzksInNwdUNvZGUiOiJDRDIwMjMwMjA4MjQ1MjQ1S1YiLCJ0cmFja2luZ0lkIjoiMTMwNTEyMjg3Nzg0MDE5ODQifQ%3D%3D&listType=2&listTitle=%EC%83%B5%EC%82%AC%EC%9D%B4%EB%8B%A4%20%EC%84%9C%EC%9A%B8%20%ED%8C%9D%EC%97%85%20%EC%8A%A4%ED%86%A0%EC%96%B4%20%EC%BB%AC%EB%A0%89%EC%85%98"
  },
  {
    "productId": 19,
    "price": "28600",
    "brandId": 1,
    "title": "래빗 니트 크롭 탱크탑",
    "wishYN": "N",
    "imgUrls": [
      "https://img1.shopcider.com/product/1681902980000-QG2Q8W.jpg?x-oss-process=image/resize,w_350,m_lfit/quality,Q_80/interlace,1",
      "https://img1.shopcider.com/product/1679020183000-BjP5BP.jpg?x-oss-process=image/resize,w_350,m_lfit/quality,Q_80/interlace,1"
    ],
    "href": "https://www.shopcider.com/goods/rabbit-knit-crop-tank-top-1033939?style_id=137855&gaListId=-----1&gaListName=%25EC%2583%25B5%25EC%2582%25AC%25EC%259D%25B4%25EB%258B%25A4%2520%25EC%2584%259C%25EC%259A%25B8%2520%25ED%258C%259D%25EC%2597%2585%2520%25EC%258A%25A4%25ED%2586%25A0%25EC%2596%25B4%2520%25EC%25BB%25AC%25EB%25A0%2589%25EC%2585%2598&ciderListId=2&ciderListName=%EC%83%B5%EC%82%AC%EC%9D%B4%EB%8B%A4%20%EC%84%9C%EC%9A%B8%20%ED%8C%9D%EC%97%85%20%EC%8A%A4%ED%86%A0%EC%96%B4%20%EC%BB%AC%EB%A0%89%EC%85%98&selectSkuIndex=0&moduleTitle=1&p=1033939&shopPage=7&shopIndex=123&navTitle=%25EC%2583%25B5%25EC%2582%25AC%25EC%259D%25B4%25EB%258B%25A4%2520%25EC%2584%259C%25EC%259A%25B8%2520%25ED%258C%259D%25EC%2597%2585%2520%25EC%258A%25A4%25ED%2586%25A0%25EC%2596%25B4%2520%25EC%25BB%25AC%25EB%25A0%2589%25EC%2585%2598&navId=-----1&listSort=&listId=11121&listAttribute=&operationContent=&operationImage=&linkUrl=&operationpageTitle=&operationPosition=&operationType=&productPosition=124&strategyNameList=&businessTracking=eyJmaXJzdEltYWdlVHlwZSI6Iuato%2BmdouS4iuWNiui6qyIsIml0ZW1UeXBlIjowLCJsaXN0SWQiOjExMTIxLCJsaXN0VGl0bGUiOiLsg7XsgqzsnbTri6Qg7ISc7Jq4IO2MneyXhSDsiqTthqDslrQg7Lus66CJ7IWYIiwibGlzdFR5cGUiOjIsIm1vZHVsZUlkIjoxLCJwcm9kdWN0UHJpbWFyeUltYWdlRmxhZyI6dHJ1ZSwic2FsZVByaWNlIjoyMy4wMCwic2tjRmlyc3RJbWciOiIxNjgxOTAyOTgwMDAwLVFHMlE4Vy5qcGciLCJzcHUiOjEwMzM5MzksInNwdUNvZGUiOiJDRDIwMjMwMjA4MjQ1MjQ1S1YiLCJ0cmFja2luZ0lkIjoiMTMwNTEyMjg3Nzg0MDE5ODQifQ%3D%3D&listType=2&listTitle=%EC%83%B5%EC%82%AC%EC%9D%B4%EB%8B%A4%20%EC%84%9C%EC%9A%B8%20%ED%8C%9D%EC%97%85%20%EC%8A%A4%ED%86%A0%EC%96%B4%20%EC%BB%AC%EB%A0%89%EC%85%98"
  },
  {
    "productId": 20,
    "price": "28600",
    "brandId": 1,
    "title": "래빗 니트 크롭 탱크탑",
    "wishYN": "N",
    "imgUrls": [
      "https://img1.shopcider.com/product/1681902980000-QG2Q8W.jpg?x-oss-process=image/resize,w_350,m_lfit/quality,Q_80/interlace,1",
      "https://img1.shopcider.com/product/1679020183000-BjP5BP.jpg?x-oss-process=image/resize,w_350,m_lfit/quality,Q_80/interlace,1"
    ],
    "href": "https://www.shopcider.com/goods/rabbit-knit-crop-tank-top-1033939?style_id=137855&gaListId=-----1&gaListName=%25EC%2583%25B5%25EC%2582%25AC%25EC%259D%25B4%25EB%258B%25A4%2520%25EC%2584%259C%25EC%259A%25B8%2520%25ED%258C%259D%25EC%2597%2585%2520%25EC%258A%25A4%25ED%2586%25A0%25EC%2596%25B4%2520%25EC%25BB%25AC%25EB%25A0%2589%25EC%2585%2598&ciderListId=2&ciderListName=%EC%83%B5%EC%82%AC%EC%9D%B4%EB%8B%A4%20%EC%84%9C%EC%9A%B8%20%ED%8C%9D%EC%97%85%20%EC%8A%A4%ED%86%A0%EC%96%B4%20%EC%BB%AC%EB%A0%89%EC%85%98&selectSkuIndex=0&moduleTitle=1&p=1033939&shopPage=7&shopIndex=123&navTitle=%25EC%2583%25B5%25EC%2582%25AC%25EC%259D%25B4%25EB%258B%25A4%2520%25EC%2584%259C%25EC%259A%25B8%2520%25ED%258C%259D%25EC%2597%2585%2520%25EC%258A%25A4%25ED%2586%25A0%25EC%2596%25B4%2520%25EC%25BB%25AC%25EB%25A0%2589%25EC%2585%2598&navId=-----1&listSort=&listId=11121&listAttribute=&operationContent=&operationImage=&linkUrl=&operationpageTitle=&operationPosition=&operationType=&productPosition=124&strategyNameList=&businessTracking=eyJmaXJzdEltYWdlVHlwZSI6Iuato%2BmdouS4iuWNiui6qyIsIml0ZW1UeXBlIjowLCJsaXN0SWQiOjExMTIxLCJsaXN0VGl0bGUiOiLsg7XsgqzsnbTri6Qg7ISc7Jq4IO2MneyXhSDsiqTthqDslrQg7Lus66CJ7IWYIiwibGlzdFR5cGUiOjIsIm1vZHVsZUlkIjoxLCJwcm9kdWN0UHJpbWFyeUltYWdlRmxhZyI6dHJ1ZSwic2FsZVByaWNlIjoyMy4wMCwic2tjRmlyc3RJbWciOiIxNjgxOTAyOTgwMDAwLVFHMlE4Vy5qcGciLCJzcHUiOjEwMzM5MzksInNwdUNvZGUiOiJDRDIwMjMwMjA4MjQ1MjQ1S1YiLCJ0cmFja2luZ0lkIjoiMTMwNTEyMjg3Nzg0MDE5ODQifQ%3D%3D&listType=2&listTitle=%EC%83%B5%EC%82%AC%EC%9D%B4%EB%8B%A4%20%EC%84%9C%EC%9A%B8%20%ED%8C%9D%EC%97%85%20%EC%8A%A4%ED%86%A0%EC%96%B4%20%EC%BB%AC%EB%A0%89%EC%85%98"
  },
  {
    "productId": 21,
    "price": "28600",
    "brandId": 1,
    "title": "래빗 니트 크롭 탱크탑",
    "wishYN": "N",
    "imgUrls": [
      "https://img1.shopcider.com/product/1681902980000-QG2Q8W.jpg?x-oss-process=image/resize,w_350,m_lfit/quality,Q_80/interlace,1",
      "https://img1.shopcider.com/product/1679020183000-BjP5BP.jpg?x-oss-process=image/resize,w_350,m_lfit/quality,Q_80/interlace,1"
    ],
    "href": "https://www.shopcider.com/goods/rabbit-knit-crop-tank-top-1033939?style_id=137855&gaListId=-----1&gaListName=%25EC%2583%25B5%25EC%2582%25AC%25EC%259D%25B4%25EB%258B%25A4%2520%25EC%2584%259C%25EC%259A%25B8%2520%25ED%258C%259D%25EC%2597%2585%2520%25EC%258A%25A4%25ED%2586%25A0%25EC%2596%25B4%2520%25EC%25BB%25AC%25EB%25A0%2589%25EC%2585%2598&ciderListId=2&ciderListName=%EC%83%B5%EC%82%AC%EC%9D%B4%EB%8B%A4%20%EC%84%9C%EC%9A%B8%20%ED%8C%9D%EC%97%85%20%EC%8A%A4%ED%86%A0%EC%96%B4%20%EC%BB%AC%EB%A0%89%EC%85%98&selectSkuIndex=0&moduleTitle=1&p=1033939&shopPage=7&shopIndex=123&navTitle=%25EC%2583%25B5%25EC%2582%25AC%25EC%259D%25B4%25EB%258B%25A4%2520%25EC%2584%259C%25EC%259A%25B8%2520%25ED%258C%259D%25EC%2597%2585%2520%25EC%258A%25A4%25ED%2586%25A0%25EC%2596%25B4%2520%25EC%25BB%25AC%25EB%25A0%2589%25EC%2585%2598&navId=-----1&listSort=&listId=11121&listAttribute=&operationContent=&operationImage=&linkUrl=&operationpageTitle=&operationPosition=&operationType=&productPosition=124&strategyNameList=&businessTracking=eyJmaXJzdEltYWdlVHlwZSI6Iuato%2BmdouS4iuWNiui6qyIsIml0ZW1UeXBlIjowLCJsaXN0SWQiOjExMTIxLCJsaXN0VGl0bGUiOiLsg7XsgqzsnbTri6Qg7ISc7Jq4IO2MneyXhSDsiqTthqDslrQg7Lus66CJ7IWYIiwibGlzdFR5cGUiOjIsIm1vZHVsZUlkIjoxLCJwcm9kdWN0UHJpbWFyeUltYWdlRmxhZyI6dHJ1ZSwic2FsZVByaWNlIjoyMy4wMCwic2tjRmlyc3RJbWciOiIxNjgxOTAyOTgwMDAwLVFHMlE4Vy5qcGciLCJzcHUiOjEwMzM5MzksInNwdUNvZGUiOiJDRDIwMjMwMjA4MjQ1MjQ1S1YiLCJ0cmFja2luZ0lkIjoiMTMwNTEyMjg3Nzg0MDE5ODQifQ%3D%3D&listType=2&listTitle=%EC%83%B5%EC%82%AC%EC%9D%B4%EB%8B%A4%20%EC%84%9C%EC%9A%B8%20%ED%8C%9D%EC%97%85%20%EC%8A%A4%ED%86%A0%EC%96%B4%20%EC%BB%AC%EB%A0%89%EC%85%98"
  },
  {
    "productId": 22,
    "price": "28600",
    "brandId": 1,
    "title": "래빗 니트 크롭 탱크탑",
    "wishYN": "N",
    "imgUrls": [
      "https://img1.shopcider.com/product/1681902980000-QG2Q8W.jpg?x-oss-process=image/resize,w_350,m_lfit/quality,Q_80/interlace,1",
      "https://img1.shopcider.com/product/1679020183000-BjP5BP.jpg?x-oss-process=image/resize,w_350,m_lfit/quality,Q_80/interlace,1"
    ],
    "href": "https://www.shopcider.com/goods/rabbit-knit-crop-tank-top-1033939?style_id=137855&gaListId=-----1&gaListName=%25EC%2583%25B5%25EC%2582%25AC%25EC%259D%25B4%25EB%258B%25A4%2520%25EC%2584%259C%25EC%259A%25B8%2520%25ED%258C%259D%25EC%2597%2585%2520%25EC%258A%25A4%25ED%2586%25A0%25EC%2596%25B4%2520%25EC%25BB%25AC%25EB%25A0%2589%25EC%2585%2598&ciderListId=2&ciderListName=%EC%83%B5%EC%82%AC%EC%9D%B4%EB%8B%A4%20%EC%84%9C%EC%9A%B8%20%ED%8C%9D%EC%97%85%20%EC%8A%A4%ED%86%A0%EC%96%B4%20%EC%BB%AC%EB%A0%89%EC%85%98&selectSkuIndex=0&moduleTitle=1&p=1033939&shopPage=7&shopIndex=123&navTitle=%25EC%2583%25B5%25EC%2582%25AC%25EC%259D%25B4%25EB%258B%25A4%2520%25EC%2584%259C%25EC%259A%25B8%2520%25ED%258C%259D%25EC%2597%2585%2520%25EC%258A%25A4%25ED%2586%25A0%25EC%2596%25B4%2520%25EC%25BB%25AC%25EB%25A0%2589%25EC%2585%2598&navId=-----1&listSort=&listId=11121&listAttribute=&operationContent=&operationImage=&linkUrl=&operationpageTitle=&operationPosition=&operationType=&productPosition=124&strategyNameList=&businessTracking=eyJmaXJzdEltYWdlVHlwZSI6Iuato%2BmdouS4iuWNiui6qyIsIml0ZW1UeXBlIjowLCJsaXN0SWQiOjExMTIxLCJsaXN0VGl0bGUiOiLsg7XsgqzsnbTri6Qg7ISc7Jq4IO2MneyXhSDsiqTthqDslrQg7Lus66CJ7IWYIiwibGlzdFR5cGUiOjIsIm1vZHVsZUlkIjoxLCJwcm9kdWN0UHJpbWFyeUltYWdlRmxhZyI6dHJ1ZSwic2FsZVByaWNlIjoyMy4wMCwic2tjRmlyc3RJbWciOiIxNjgxOTAyOTgwMDAwLVFHMlE4Vy5qcGciLCJzcHUiOjEwMzM5MzksInNwdUNvZGUiOiJDRDIwMjMwMjA4MjQ1MjQ1S1YiLCJ0cmFja2luZ0lkIjoiMTMwNTEyMjg3Nzg0MDE5ODQifQ%3D%3D&listType=2&listTitle=%EC%83%B5%EC%82%AC%EC%9D%B4%EB%8B%A4%20%EC%84%9C%EC%9A%B8%20%ED%8C%9D%EC%97%85%20%EC%8A%A4%ED%86%A0%EC%96%B4%20%EC%BB%AC%EB%A0%89%EC%85%98"
  },
  {
    "productId": 23,
    "price": "28600",
    "brandId": 1,

    "title": "래빗 니트 크롭 탱크탑",
    "wishYN": "N",
    "imgUrls": [
      "https://img1.shopcider.com/product/1681902980000-QG2Q8W.jpg?x-oss-process=image/resize,w_350,m_lfit/quality,Q_80/interlace,1",
      "https://img1.shopcider.com/product/1679020183000-BjP5BP.jpg?x-oss-process=image/resize,w_350,m_lfit/quality,Q_80/interlace,1"
    ],
    "href": "https://www.shopcider.com/goods/rabbit-knit-crop-tank-top-1033939?style_id=137855&gaListId=-----1&gaListName=%25EC%2583%25B5%25EC%2582%25AC%25EC%259D%25B4%25EB%258B%25A4%2520%25EC%2584%259C%25EC%259A%25B8%2520%25ED%258C%259D%25EC%2597%2585%2520%25EC%258A%25A4%25ED%2586%25A0%25EC%2596%25B4%2520%25EC%25BB%25AC%25EB%25A0%2589%25EC%2585%2598&ciderListId=2&ciderListName=%EC%83%B5%EC%82%AC%EC%9D%B4%EB%8B%A4%20%EC%84%9C%EC%9A%B8%20%ED%8C%9D%EC%97%85%20%EC%8A%A4%ED%86%A0%EC%96%B4%20%EC%BB%AC%EB%A0%89%EC%85%98&selectSkuIndex=0&moduleTitle=1&p=1033939&shopPage=7&shopIndex=123&navTitle=%25EC%2583%25B5%25EC%2582%25AC%25EC%259D%25B4%25EB%258B%25A4%2520%25EC%2584%259C%25EC%259A%25B8%2520%25ED%258C%259D%25EC%2597%2585%2520%25EC%258A%25A4%25ED%2586%25A0%25EC%2596%25B4%2520%25EC%25BB%25AC%25EB%25A0%2589%25EC%2585%2598&navId=-----1&listSort=&listId=11121&listAttribute=&operationContent=&operationImage=&linkUrl=&operationpageTitle=&operationPosition=&operationType=&productPosition=124&strategyNameList=&businessTracking=eyJmaXJzdEltYWdlVHlwZSI6Iuato%2BmdouS4iuWNiui6qyIsIml0ZW1UeXBlIjowLCJsaXN0SWQiOjExMTIxLCJsaXN0VGl0bGUiOiLsg7XsgqzsnbTri6Qg7ISc7Jq4IO2MneyXhSDsiqTthqDslrQg7Lus66CJ7IWYIiwibGlzdFR5cGUiOjIsIm1vZHVsZUlkIjoxLCJwcm9kdWN0UHJpbWFyeUltYWdlRmxhZyI6dHJ1ZSwic2FsZVByaWNlIjoyMy4wMCwic2tjRmlyc3RJbWciOiIxNjgxOTAyOTgwMDAwLVFHMlE4Vy5qcGciLCJzcHUiOjEwMzM5MzksInNwdUNvZGUiOiJDRDIwMjMwMjA4MjQ1MjQ1S1YiLCJ0cmFja2luZ0lkIjoiMTMwNTEyMjg3Nzg0MDE5ODQifQ%3D%3D&listType=2&listTitle=%EC%83%B5%EC%82%AC%EC%9D%B4%EB%8B%A4%20%EC%84%9C%EC%9A%B8%20%ED%8C%9D%EC%97%85%20%EC%8A%A4%ED%86%A0%EC%96%B4%20%EC%BB%AC%EB%A0%89%EC%85%98"
  },
  {
    "productId": 24,
    "price": "20800",
    "brandId": 1,
    "title": "버튼업 반팔 크롭 후드탑",
    "wishYN": "N",
    "imgUrls": [
      "https://img1.shopcider.com/product/1679318783000-cPaQMb.jpg?x-oss-process=image/resize,w_350,m_lfit/quality,Q_80/interlace,1",
      "https://img1.shopcider.com/product/1679318783000-Xh5N2J.jpg?x-oss-process=image/resize,w_350,m_lfit/quality,Q_80/interlace,1"
    ],
    "href": ""
  },
  {
    "productId": 25,
    "price": "28600",
    "brandId": 1,
    "title": "카라 버튼 다운 블라우스",
    "wishYN": "N",
    "imgUrls": [
      "https://img1.shopcider.com/product/1659755930000-2zwJic.jpg?x-oss-process=image/resize,w_350,m_lfit/quality,Q_80/interlace,1",
      "https://img1.shopcider.com/product/1659755930000-MiM5yD.jpg?x-oss-process=image/resize,w_350,m_lfit/quality,Q_80/interlace,1"
    ],
    "href": ""
  },
  {
    "productId": 26,
    "price": "26000",
    "brandId": 1,
    "title": "솔리드 텍스처 칼라 크롭 탑",
    "wishYN": "N",
    "imgUrls": [
      "https://img1.shopcider.com/product/1648628969000-KfCtWT.jpg?x-oss-process=image/resize,w_350,m_lfit/quality,Q_80/interlace,1",
      "https://img.shopcider.com/hermes/video/1689833562000-2kxaca.jpg?x-oss-process=image/resize,w_350,m_lfit/quality,Q_80/interlace,1"
    ],
    "href": ""
  },
  {
    "productId": 27,
    "price": "18200",
    "brandId": 1,
    "title": "Keep Rolling 그래픽 크롭 탑",
    "wishYN": "N",
    "imgUrls": [
      "https://img1.shopcider.com/product/1658730470000-DycYZ2.jpg?x-oss-process=image/resize,w_350,m_lfit/quality,Q_80/interlace,1",
      "https://img1.shopcider.com/product/1659419253000-bTdmp8.jpg?x-oss-process=image/resize,w_350,m_lfit/quality,Q_80/interlace,1"
    ],
    "href": ""
  },
  {
    "productId": 28,
    "price": "13200",
    "brandId": 1,
    "title": "버클 U넥 반팔탑",
    "wishYN": "N",
    "imgUrls": [
      "https://img1.shopcider.com/product/1680947912000-EdNB5z.jpg?x-oss-process=image/resize,w_350,m_lfit/quality,Q_80/interlace,1",
      "https://img1.shopcider.com/product/1680947912000-DWrw2T.jpg?x-oss-process=image/resize,w_350,m_lfit/quality,Q_80/interlace,1"
    ],
    "href": ""
  },
  {
    "productId": 29,
    "price": "26000",
    "brandId": 1,
    "title": "솔리드 미들 웨이스트 플리츠 스커트",
    "wishYN": "N",
    "imgUrls": [
      "https://img1.shopcider.com/product/1672226822000-wKRSMp.jpg?x-oss-process=image/resize,w_350,m_lfit/quality,Q_80/interlace,1",
      "https://img.shopcider.com/hermes/video/1680506294000-7jq6dz.jpg?x-oss-process=image/resize,w_350,m_lfit/quality,Q_80/interlace,1"
    ],
    "href": ""
  },
  {
    "productId": 30,
    "price": "22800",
    "brandId": 1,
    "title": "저지 플라워 그래픽 반팔 탑셔츠",
    "wishYN": "N",
    "imgUrls": [
      "https://img1.shopcider.com/product/1675236673000-8yinH6.jpg?x-oss-process=image/resize,w_350,m_lfit/quality,Q_80/interlace,1",
      "https://img1.shopcider.com/product/1675236673000-JZwbJf.jpg?x-oss-process=image/resize,w_350,m_lfit/quality,Q_80/interlace,1"
    ],
    "href": ""
  },
  {
    "productId": 31,
    "price": "28600",
    "brandId": 1,
    "title": "래빗 니트 크롭 탱크탑",
    "wishYN": "N",
    "imgUrls": [
      "https://img1.shopcider.com/product/1681902980000-QG2Q8W.jpg?x-oss-process=image/resize,w_350,m_lfit/quality,Q_80/interlace,1",
      "https://img1.shopcider.com/product/1679020183000-BjP5BP.jpg?x-oss-process=image/resize,w_350,m_lfit/quality,Q_80/interlace,1"
    ],
    "href": "https://www.shopcider.com/goods/rabbit-knit-crop-tank-top-1033939?style_id=137855&gaListId=-----1&gaListName=%25EC%2583%25B5%25EC%2582%25AC%25EC%259D%25B4%25EB%258B%25A4%2520%25EC%2584%259C%25EC%259A%25B8%2520%25ED%258C%259D%25EC%2597%2585%2520%25EC%258A%25A4%25ED%2586%25A0%25EC%2596%25B4%2520%25EC%25BB%25AC%25EB%25A0%2589%25EC%2585%2598&ciderListId=2&ciderListName=%EC%83%B5%EC%82%AC%EC%9D%B4%EB%8B%A4%20%EC%84%9C%EC%9A%B8%20%ED%8C%9D%EC%97%85%20%EC%8A%A4%ED%86%A0%EC%96%B4%20%EC%BB%AC%EB%A0%89%EC%85%98&selectSkuIndex=0&moduleTitle=1&p=1033939&shopPage=7&shopIndex=123&navTitle=%25EC%2583%25B5%25EC%2582%25AC%25EC%259D%25B4%25EB%258B%25A4%2520%25EC%2584%259C%25EC%259A%25B8%2520%25ED%258C%259D%25EC%2597%2585%2520%25EC%258A%25A4%25ED%2586%25A0%25EC%2596%25B4%2520%25EC%25BB%25AC%25EB%25A0%2589%25EC%2585%2598&navId=-----1&listSort=&listId=11121&listAttribute=&operationContent=&operationImage=&linkUrl=&operationpageTitle=&operationPosition=&operationType=&productPosition=124&strategyNameList=&businessTracking=eyJmaXJzdEltYWdlVHlwZSI6Iuato%2BmdouS4iuWNiui6qyIsIml0ZW1UeXBlIjowLCJsaXN0SWQiOjExMTIxLCJsaXN0VGl0bGUiOiLsg7XsgqzsnbTri6Qg7ISc7Jq4IO2MneyXhSDsiqTthqDslrQg7Lus66CJ7IWYIiwibGlzdFR5cGUiOjIsIm1vZHVsZUlkIjoxLCJwcm9kdWN0UHJpbWFyeUltYWdlRmxhZyI6dHJ1ZSwic2FsZVByaWNlIjoyMy4wMCwic2tjRmlyc3RJbWciOiIxNjgxOTAyOTgwMDAwLVFHMlE4Vy5qcGciLCJzcHUiOjEwMzM5MzksInNwdUNvZGUiOiJDRDIwMjMwMjA4MjQ1MjQ1S1YiLCJ0cmFja2luZ0lkIjoiMTMwNTEyMjg3Nzg0MDE5ODQifQ%3D%3D&listType=2&listTitle=%EC%83%B5%EC%82%AC%EC%9D%B4%EB%8B%A4%20%EC%84%9C%EC%9A%B8%20%ED%8C%9D%EC%97%85%20%EC%8A%A4%ED%86%A0%EC%96%B4%20%EC%BB%AC%EB%A0%89%EC%85%98"
  },
  {
    "productId": 32,
    "price": "28600",
    "brandId": 1,
    "title": "래빗 니트 크롭 탱크탑",
    "wishYN": "N",
    "imgUrls": [
      "https://img1.shopcider.com/product/1681902980000-QG2Q8W.jpg?x-oss-process=image/resize,w_350,m_lfit/quality,Q_80/interlace,1",
      "https://img1.shopcider.com/product/1679020183000-BjP5BP.jpg?x-oss-process=image/resize,w_350,m_lfit/quality,Q_80/interlace,1"
    ],
    "href": "https://www.shopcider.com/goods/rabbit-knit-crop-tank-top-1033939?style_id=137855&gaListId=-----1&gaListName=%25EC%2583%25B5%25EC%2582%25AC%25EC%259D%25B4%25EB%258B%25A4%2520%25EC%2584%259C%25EC%259A%25B8%2520%25ED%258C%259D%25EC%2597%2585%2520%25EC%258A%25A4%25ED%2586%25A0%25EC%2596%25B4%2520%25EC%25BB%25AC%25EB%25A0%2589%25EC%2585%2598&ciderListId=2&ciderListName=%EC%83%B5%EC%82%AC%EC%9D%B4%EB%8B%A4%20%EC%84%9C%EC%9A%B8%20%ED%8C%9D%EC%97%85%20%EC%8A%A4%ED%86%A0%EC%96%B4%20%EC%BB%AC%EB%A0%89%EC%85%98&selectSkuIndex=0&moduleTitle=1&p=1033939&shopPage=7&shopIndex=123&navTitle=%25EC%2583%25B5%25EC%2582%25AC%25EC%259D%25B4%25EB%258B%25A4%2520%25EC%2584%259C%25EC%259A%25B8%2520%25ED%258C%259D%25EC%2597%2585%2520%25EC%258A%25A4%25ED%2586%25A0%25EC%2596%25B4%2520%25EC%25BB%25AC%25EB%25A0%2589%25EC%2585%2598&navId=-----1&listSort=&listId=11121&listAttribute=&operationContent=&operationImage=&linkUrl=&operationpageTitle=&operationPosition=&operationType=&productPosition=124&strategyNameList=&businessTracking=eyJmaXJzdEltYWdlVHlwZSI6Iuato%2BmdouS4iuWNiui6qyIsIml0ZW1UeXBlIjowLCJsaXN0SWQiOjExMTIxLCJsaXN0VGl0bGUiOiLsg7XsgqzsnbTri6Qg7ISc7Jq4IO2MneyXhSDsiqTthqDslrQg7Lus66CJ7IWYIiwibGlzdFR5cGUiOjIsIm1vZHVsZUlkIjoxLCJwcm9kdWN0UHJpbWFyeUltYWdlRmxhZyI6dHJ1ZSwic2FsZVByaWNlIjoyMy4wMCwic2tjRmlyc3RJbWciOiIxNjgxOTAyOTgwMDAwLVFHMlE4Vy5qcGciLCJzcHUiOjEwMzM5MzksInNwdUNvZGUiOiJDRDIwMjMwMjA4MjQ1MjQ1S1YiLCJ0cmFja2luZ0lkIjoiMTMwNTEyMjg3Nzg0MDE5ODQifQ%3D%3D&listType=2&listTitle=%EC%83%B5%EC%82%AC%EC%9D%B4%EB%8B%A4%20%EC%84%9C%EC%9A%B8%20%ED%8C%9D%EC%97%85%20%EC%8A%A4%ED%86%A0%EC%96%B4%20%EC%BB%AC%EB%A0%89%EC%85%98"
  },
  {
    "productId": 33,
    "price": "28600",
    "brandId": 1,

    "title": "래빗 니트 크롭 탱크탑",
    "wishYN": "N",
    "imgUrls": [
      "https://img1.shopcider.com/product/1681902980000-QG2Q8W.jpg?x-oss-process=image/resize,w_350,m_lfit/quality,Q_80/interlace,1",
      "https://img1.shopcider.com/product/1679020183000-BjP5BP.jpg?x-oss-process=image/resize,w_350,m_lfit/quality,Q_80/interlace,1"
    ],
    "href": "https://www.shopcider.com/goods/rabbit-knit-crop-tank-top-1033939?style_id=137855&gaListId=-----1&gaListName=%25EC%2583%25B5%25EC%2582%25AC%25EC%259D%25B4%25EB%258B%25A4%2520%25EC%2584%259C%25EC%259A%25B8%2520%25ED%258C%259D%25EC%2597%2585%2520%25EC%258A%25A4%25ED%2586%25A0%25EC%2596%25B4%2520%25EC%25BB%25AC%25EB%25A0%2589%25EC%2585%2598&ciderListId=2&ciderListName=%EC%83%B5%EC%82%AC%EC%9D%B4%EB%8B%A4%20%EC%84%9C%EC%9A%B8%20%ED%8C%9D%EC%97%85%20%EC%8A%A4%ED%86%A0%EC%96%B4%20%EC%BB%AC%EB%A0%89%EC%85%98&selectSkuIndex=0&moduleTitle=1&p=1033939&shopPage=7&shopIndex=123&navTitle=%25EC%2583%25B5%25EC%2582%25AC%25EC%259D%25B4%25EB%258B%25A4%2520%25EC%2584%259C%25EC%259A%25B8%2520%25ED%258C%259D%25EC%2597%2585%2520%25EC%258A%25A4%25ED%2586%25A0%25EC%2596%25B4%2520%25EC%25BB%25AC%25EB%25A0%2589%25EC%2585%2598&navId=-----1&listSort=&listId=11121&listAttribute=&operationContent=&operationImage=&linkUrl=&operationpageTitle=&operationPosition=&operationType=&productPosition=124&strategyNameList=&businessTracking=eyJmaXJzdEltYWdlVHlwZSI6Iuato%2BmdouS4iuWNiui6qyIsIml0ZW1UeXBlIjowLCJsaXN0SWQiOjExMTIxLCJsaXN0VGl0bGUiOiLsg7XsgqzsnbTri6Qg7ISc7Jq4IO2MneyXhSDsiqTthqDslrQg7Lus66CJ7IWYIiwibGlzdFR5cGUiOjIsIm1vZHVsZUlkIjoxLCJwcm9kdWN0UHJpbWFyeUltYWdlRmxhZyI6dHJ1ZSwic2FsZVByaWNlIjoyMy4wMCwic2tjRmlyc3RJbWciOiIxNjgxOTAyOTgwMDAwLVFHMlE4Vy5qcGciLCJzcHUiOjEwMzM5MzksInNwdUNvZGUiOiJDRDIwMjMwMjA4MjQ1MjQ1S1YiLCJ0cmFja2luZ0lkIjoiMTMwNTEyMjg3Nzg0MDE5ODQifQ%3D%3D&listType=2&listTitle=%EC%83%B5%EC%82%AC%EC%9D%B4%EB%8B%A4%20%EC%84%9C%EC%9A%B8%20%ED%8C%9D%EC%97%85%20%EC%8A%A4%ED%86%A0%EC%96%B4%20%EC%BB%AC%EB%A0%89%EC%85%98"
  },
  {
    "productId": 34,
    "price": "20800",
    "brandId": 1,
    "title": "버튼업 반팔 크롭 후드탑",
    "wishYN": "N",
    "imgUrls": [
      "https://img1.shopcider.com/product/1679318783000-cPaQMb.jpg?x-oss-process=image/resize,w_350,m_lfit/quality,Q_80/interlace,1",
      "https://img1.shopcider.com/product/1679318783000-Xh5N2J.jpg?x-oss-process=image/resize,w_350,m_lfit/quality,Q_80/interlace,1"
    ],
    "href": ""
  },
  {
    "productId": 35,
    "price": "28600",
    "brandId": 1,
    "title": "카라 버튼 다운 블라우스",
    "wishYN": "N",
    "imgUrls": [
      "https://img1.shopcider.com/product/1659755930000-2zwJic.jpg?x-oss-process=image/resize,w_350,m_lfit/quality,Q_80/interlace,1",
      "https://img1.shopcider.com/product/1659755930000-MiM5yD.jpg?x-oss-process=image/resize,w_350,m_lfit/quality,Q_80/interlace,1"
    ],
    "href": ""
  },
  {
    "productId": 36,
    "price": "26000",
    "brandId": 1,
    "title": "솔리드 텍스처 칼라 크롭 탑",
    "wishYN": "N",
    "imgUrls": [
      "https://img1.shopcider.com/product/1648628969000-KfCtWT.jpg?x-oss-process=image/resize,w_350,m_lfit/quality,Q_80/interlace,1",
      "https://img.shopcider.com/hermes/video/1689833562000-2kxaca.jpg?x-oss-process=image/resize,w_350,m_lfit/quality,Q_80/interlace,1"
    ],
    "href": ""
  },
  {
    "productId": 37,
    "price": "18200",
    "brandId": 1,
    "title": "Keep Rolling 그래픽 크롭 탑",
    "wishYN": "N",
    "imgUrls": [
      "https://img1.shopcider.com/product/1658730470000-DycYZ2.jpg?x-oss-process=image/resize,w_350,m_lfit/quality,Q_80/interlace,1",
      "https://img1.shopcider.com/product/1659419253000-bTdmp8.jpg?x-oss-process=image/resize,w_350,m_lfit/quality,Q_80/interlace,1"
    ],
    "href": ""
  },
  {
    "productId": 38,
    "price": "13200",
    "brandId": 1,
    "title": "버클 U넥 반팔탑",
    "wishYN": "N",
    "imgUrls": [
      "https://img1.shopcider.com/product/1680947912000-EdNB5z.jpg?x-oss-process=image/resize,w_350,m_lfit/quality,Q_80/interlace,1",
      "https://img1.shopcider.com/product/1680947912000-DWrw2T.jpg?x-oss-process=image/resize,w_350,m_lfit/quality,Q_80/interlace,1"
    ],
    "href": ""
  },
  {
    "productId": 39,
    "price": "26000",
    "brandId": 1,
    "title": "솔리드 미들 웨이스트 플리츠 스커트",
    "wishYN": "N",
    "imgUrls": [
      "https://img1.shopcider.com/product/1672226822000-wKRSMp.jpg?x-oss-process=image/resize,w_350,m_lfit/quality,Q_80/interlace,1",
      "https://img.shopcider.com/hermes/video/1680506294000-7jq6dz.jpg?x-oss-process=image/resize,w_350,m_lfit/quality,Q_80/interlace,1"
    ],
    "href": ""
  },
  {
    "productId": 40,
    "price": "28600",
    "brandId": 1,
    "title": "래빗 니트 크롭 탱크탑",
    "wishYN": "N",
    "imgUrls": [
      "https://img1.shopcider.com/product/1681902980000-QG2Q8W.jpg?x-oss-process=image/resize,w_350,m_lfit/quality,Q_80/interlace,1",
      "https://img1.shopcider.com/product/1679020183000-BjP5BP.jpg?x-oss-process=image/resize,w_350,m_lfit/quality,Q_80/interlace,1"
    ],
    "href": "https://www.shopcider.com/goods/rabbit-knit-crop-tank-top-1033939?style_id=137855&gaListId=-----1&gaListName=%25EC%2583%25B5%25EC%2582%25AC%25EC%259D%25B4%25EB%258B%25A4%2520%25EC%2584%259C%25EC%259A%25B8%2520%25ED%258C%259D%25EC%2597%2585%2520%25EC%258A%25A4%25ED%2586%25A0%25EC%2596%25B4%2520%25EC%25BB%25AC%25EB%25A0%2589%25EC%2585%2598&ciderListId=2&ciderListName=%EC%83%B5%EC%82%AC%EC%9D%B4%EB%8B%A4%20%EC%84%9C%EC%9A%B8%20%ED%8C%9D%EC%97%85%20%EC%8A%A4%ED%86%A0%EC%96%B4%20%EC%BB%AC%EB%A0%89%EC%85%98&selectSkuIndex=0&moduleTitle=1&p=1033939&shopPage=7&shopIndex=123&navTitle=%25EC%2583%25B5%25EC%2582%25AC%25EC%259D%25B4%25EB%258B%25A4%2520%25EC%2584%259C%25EC%259A%25B8%2520%25ED%258C%259D%25EC%2597%2585%2520%25EC%258A%25A4%25ED%2586%25A0%25EC%2596%25B4%2520%25EC%25BB%25AC%25EB%25A0%2589%25EC%2585%2598&navId=-----1&listSort=&listId=11121&listAttribute=&operationContent=&operationImage=&linkUrl=&operationpageTitle=&operationPosition=&operationType=&productPosition=124&strategyNameList=&businessTracking=eyJmaXJzdEltYWdlVHlwZSI6Iuato%2BmdouS4iuWNiui6qyIsIml0ZW1UeXBlIjowLCJsaXN0SWQiOjExMTIxLCJsaXN0VGl0bGUiOiLsg7XsgqzsnbTri6Qg7ISc7Jq4IO2MneyXhSDsiqTthqDslrQg7Lus66CJ7IWYIiwibGlzdFR5cGUiOjIsIm1vZHVsZUlkIjoxLCJwcm9kdWN0UHJpbWFyeUltYWdlRmxhZyI6dHJ1ZSwic2FsZVByaWNlIjoyMy4wMCwic2tjRmlyc3RJbWciOiIxNjgxOTAyOTgwMDAwLVFHMlE4Vy5qcGciLCJzcHUiOjEwMzM5MzksInNwdUNvZGUiOiJDRDIwMjMwMjA4MjQ1MjQ1S1YiLCJ0cmFja2luZ0lkIjoiMTMwNTEyMjg3Nzg0MDE5ODQifQ%3D%3D&listType=2&listTitle=%EC%83%B5%EC%82%AC%EC%9D%B4%EB%8B%A4%20%EC%84%9C%EC%9A%B8%20%ED%8C%9D%EC%97%85%20%EC%8A%A4%ED%86%A0%EC%96%B4%20%EC%BB%AC%EB%A0%89%EC%85%98"
  },
  {
    "productId": 41,
    "price": "28600",
    "brandId": 1,
    "title": "래빗 니트 크롭 탱크탑",
    "wishYN": "N",
    "imgUrls": [
      "https://img1.shopcider.com/product/1681902980000-QG2Q8W.jpg?x-oss-process=image/resize,w_350,m_lfit/quality,Q_80/interlace,1",
      "https://img1.shopcider.com/product/1679020183000-BjP5BP.jpg?x-oss-process=image/resize,w_350,m_lfit/quality,Q_80/interlace,1"
    ],
    "href": "https://www.shopcider.com/goods/rabbit-knit-crop-tank-top-1033939?style_id=137855&gaListId=-----1&gaListName=%25EC%2583%25B5%25EC%2582%25AC%25EC%259D%25B4%25EB%258B%25A4%2520%25EC%2584%259C%25EC%259A%25B8%2520%25ED%258C%259D%25EC%2597%2585%2520%25EC%258A%25A4%25ED%2586%25A0%25EC%2596%25B4%2520%25EC%25BB%25AC%25EB%25A0%2589%25EC%2585%2598&ciderListId=2&ciderListName=%EC%83%B5%EC%82%AC%EC%9D%B4%EB%8B%A4%20%EC%84%9C%EC%9A%B8%20%ED%8C%9D%EC%97%85%20%EC%8A%A4%ED%86%A0%EC%96%B4%20%EC%BB%AC%EB%A0%89%EC%85%98&selectSkuIndex=0&moduleTitle=1&p=1033939&shopPage=7&shopIndex=123&navTitle=%25EC%2583%25B5%25EC%2582%25AC%25EC%259D%25B4%25EB%258B%25A4%2520%25EC%2584%259C%25EC%259A%25B8%2520%25ED%258C%259D%25EC%2597%2585%2520%25EC%258A%25A4%25ED%2586%25A0%25EC%2596%25B4%2520%25EC%25BB%25AC%25EB%25A0%2589%25EC%2585%2598&navId=-----1&listSort=&listId=11121&listAttribute=&operationContent=&operationImage=&linkUrl=&operationpageTitle=&operationPosition=&operationType=&productPosition=124&strategyNameList=&businessTracking=eyJmaXJzdEltYWdlVHlwZSI6Iuato%2BmdouS4iuWNiui6qyIsIml0ZW1UeXBlIjowLCJsaXN0SWQiOjExMTIxLCJsaXN0VGl0bGUiOiLsg7XsgqzsnbTri6Qg7ISc7Jq4IO2MneyXhSDsiqTthqDslrQg7Lus66CJ7IWYIiwibGlzdFR5cGUiOjIsIm1vZHVsZUlkIjoxLCJwcm9kdWN0UHJpbWFyeUltYWdlRmxhZyI6dHJ1ZSwic2FsZVByaWNlIjoyMy4wMCwic2tjRmlyc3RJbWciOiIxNjgxOTAyOTgwMDAwLVFHMlE4Vy5qcGciLCJzcHUiOjEwMzM5MzksInNwdUNvZGUiOiJDRDIwMjMwMjA4MjQ1MjQ1S1YiLCJ0cmFja2luZ0lkIjoiMTMwNTEyMjg3Nzg0MDE5ODQifQ%3D%3D&listType=2&listTitle=%EC%83%B5%EC%82%AC%EC%9D%B4%EB%8B%A4%20%EC%84%9C%EC%9A%B8%20%ED%8C%9D%EC%97%85%20%EC%8A%A4%ED%86%A0%EC%96%B4%20%EC%BB%AC%EB%A0%89%EC%85%98"
  },
  {
    "productId": 42,
    "price": "28600",
    "brandId": 1,
    "title": "래빗 니트 크롭 탱크탑",
    "wishYN": "N",
    "imgUrls": [
      "https://img1.shopcider.com/product/1681902980000-QG2Q8W.jpg?x-oss-process=image/resize,w_350,m_lfit/quality,Q_80/interlace,1",
      "https://img1.shopcider.com/product/1679020183000-BjP5BP.jpg?x-oss-process=image/resize,w_350,m_lfit/quality,Q_80/interlace,1"
    ],
    "href": "https://www.shopcider.com/goods/rabbit-knit-crop-tank-top-1033939?style_id=137855&gaListId=-----1&gaListName=%25EC%2583%25B5%25EC%2582%25AC%25EC%259D%25B4%25EB%258B%25A4%2520%25EC%2584%259C%25EC%259A%25B8%2520%25ED%258C%259D%25EC%2597%2585%2520%25EC%258A%25A4%25ED%2586%25A0%25EC%2596%25B4%2520%25EC%25BB%25AC%25EB%25A0%2589%25EC%2585%2598&ciderListId=2&ciderListName=%EC%83%B5%EC%82%AC%EC%9D%B4%EB%8B%A4%20%EC%84%9C%EC%9A%B8%20%ED%8C%9D%EC%97%85%20%EC%8A%A4%ED%86%A0%EC%96%B4%20%EC%BB%AC%EB%A0%89%EC%85%98&selectSkuIndex=0&moduleTitle=1&p=1033939&shopPage=7&shopIndex=123&navTitle=%25EC%2583%25B5%25EC%2582%25AC%25EC%259D%25B4%25EB%258B%25A4%2520%25EC%2584%259C%25EC%259A%25B8%2520%25ED%258C%259D%25EC%2597%2585%2520%25EC%258A%25A4%25ED%2586%25A0%25EC%2596%25B4%2520%25EC%25BB%25AC%25EB%25A0%2589%25EC%2585%2598&navId=-----1&listSort=&listId=11121&listAttribute=&operationContent=&operationImage=&linkUrl=&operationpageTitle=&operationPosition=&operationType=&productPosition=124&strategyNameList=&businessTracking=eyJmaXJzdEltYWdlVHlwZSI6Iuato%2BmdouS4iuWNiui6qyIsIml0ZW1UeXBlIjowLCJsaXN0SWQiOjExMTIxLCJsaXN0VGl0bGUiOiLsg7XsgqzsnbTri6Qg7ISc7Jq4IO2MneyXhSDsiqTthqDslrQg7Lus66CJ7IWYIiwibGlzdFR5cGUiOjIsIm1vZHVsZUlkIjoxLCJwcm9kdWN0UHJpbWFyeUltYWdlRmxhZyI6dHJ1ZSwic2FsZVByaWNlIjoyMy4wMCwic2tjRmlyc3RJbWciOiIxNjgxOTAyOTgwMDAwLVFHMlE4Vy5qcGciLCJzcHUiOjEwMzM5MzksInNwdUNvZGUiOiJDRDIwMjMwMjA4MjQ1MjQ1S1YiLCJ0cmFja2luZ0lkIjoiMTMwNTEyMjg3Nzg0MDE5ODQifQ%3D%3D&listType=2&listTitle=%EC%83%B5%EC%82%AC%EC%9D%B4%EB%8B%A4%20%EC%84%9C%EC%9A%B8%20%ED%8C%9D%EC%97%85%20%EC%8A%A4%ED%86%A0%EC%96%B4%20%EC%BB%AC%EB%A0%89%EC%85%98"
  },
  {
    "productId": 43,
    "price": "28600",
    "brandId": 1,

    "title": "래빗 니트 크롭 탱크탑",
    "wishYN": "N",
    "imgUrls": [
      "https://img1.shopcider.com/product/1681902980000-QG2Q8W.jpg?x-oss-process=image/resize,w_350,m_lfit/quality,Q_80/interlace,1",
      "https://img1.shopcider.com/product/1679020183000-BjP5BP.jpg?x-oss-process=image/resize,w_350,m_lfit/quality,Q_80/interlace,1"
    ],
    "href": "https://www.shopcider.com/goods/rabbit-knit-crop-tank-top-1033939?style_id=137855&gaListId=-----1&gaListName=%25EC%2583%25B5%25EC%2582%25AC%25EC%259D%25B4%25EB%258B%25A4%2520%25EC%2584%259C%25EC%259A%25B8%2520%25ED%258C%259D%25EC%2597%2585%2520%25EC%258A%25A4%25ED%2586%25A0%25EC%2596%25B4%2520%25EC%25BB%25AC%25EB%25A0%2589%25EC%2585%2598&ciderListId=2&ciderListName=%EC%83%B5%EC%82%AC%EC%9D%B4%EB%8B%A4%20%EC%84%9C%EC%9A%B8%20%ED%8C%9D%EC%97%85%20%EC%8A%A4%ED%86%A0%EC%96%B4%20%EC%BB%AC%EB%A0%89%EC%85%98&selectSkuIndex=0&moduleTitle=1&p=1033939&shopPage=7&shopIndex=123&navTitle=%25EC%2583%25B5%25EC%2582%25AC%25EC%259D%25B4%25EB%258B%25A4%2520%25EC%2584%259C%25EC%259A%25B8%2520%25ED%258C%259D%25EC%2597%2585%2520%25EC%258A%25A4%25ED%2586%25A0%25EC%2596%25B4%2520%25EC%25BB%25AC%25EB%25A0%2589%25EC%2585%2598&navId=-----1&listSort=&listId=11121&listAttribute=&operationContent=&operationImage=&linkUrl=&operationpageTitle=&operationPosition=&operationType=&productPosition=124&strategyNameList=&businessTracking=eyJmaXJzdEltYWdlVHlwZSI6Iuato%2BmdouS4iuWNiui6qyIsIml0ZW1UeXBlIjowLCJsaXN0SWQiOjExMTIxLCJsaXN0VGl0bGUiOiLsg7XsgqzsnbTri6Qg7ISc7Jq4IO2MneyXhSDsiqTthqDslrQg7Lus66CJ7IWYIiwibGlzdFR5cGUiOjIsIm1vZHVsZUlkIjoxLCJwcm9kdWN0UHJpbWFyeUltYWdlRmxhZyI6dHJ1ZSwic2FsZVByaWNlIjoyMy4wMCwic2tjRmlyc3RJbWciOiIxNjgxOTAyOTgwMDAwLVFHMlE4Vy5qcGciLCJzcHUiOjEwMzM5MzksInNwdUNvZGUiOiJDRDIwMjMwMjA4MjQ1MjQ1S1YiLCJ0cmFja2luZ0lkIjoiMTMwNTEyMjg3Nzg0MDE5ODQifQ%3D%3D&listType=2&listTitle=%EC%83%B5%EC%82%AC%EC%9D%B4%EB%8B%A4%20%EC%84%9C%EC%9A%B8%20%ED%8C%9D%EC%97%85%20%EC%8A%A4%ED%86%A0%EC%96%B4%20%EC%BB%AC%EB%A0%89%EC%85%98"
  },
  {
    "productId": 44,
    "price": "20800",
    "brandId": 1,
    "title": "버튼업 반팔 크롭 후드탑",
    "wishYN": "N",
    "imgUrls": [
      "https://img1.shopcider.com/product/1679318783000-cPaQMb.jpg?x-oss-process=image/resize,w_350,m_lfit/quality,Q_80/interlace,1",
      "https://img1.shopcider.com/product/1679318783000-Xh5N2J.jpg?x-oss-process=image/resize,w_350,m_lfit/quality,Q_80/interlace,1"
    ],
    "href": ""
  },
  {
    "productId": 45,
    "price": "28600",
    "brandId": 1,
    "title": "카라 버튼 다운 블라우스",
    "wishYN": "N",
    "imgUrls": [
      "https://img1.shopcider.com/product/1659755930000-2zwJic.jpg?x-oss-process=image/resize,w_350,m_lfit/quality,Q_80/interlace,1",
      "https://img1.shopcider.com/product/1659755930000-MiM5yD.jpg?x-oss-process=image/resize,w_350,m_lfit/quality,Q_80/interlace,1"
    ],
    "href": ""
  },
  {
    "productId": 46,
    "price": "26000",
    "brandId": 1,
    "title": "솔리드 텍스처 칼라 크롭 탑",
    "wishYN": "N",
    "imgUrls": [
      "https://img1.shopcider.com/product/1648628969000-KfCtWT.jpg?x-oss-process=image/resize,w_350,m_lfit/quality,Q_80/interlace,1",
      "https://img.shopcider.com/hermes/video/1689833562000-2kxaca.jpg?x-oss-process=image/resize,w_350,m_lfit/quality,Q_80/interlace,1"
    ],
    "href": ""
  },
  {
    "productId": 47,
    "price": "18200",
    "brandId": 1,
    "title": "Keep Rolling 그래픽 크롭 탑",
    "wishYN": "N",
    "imgUrls": [
      "https://img1.shopcider.com/product/1658730470000-DycYZ2.jpg?x-oss-process=image/resize,w_350,m_lfit/quality,Q_80/interlace,1",
      "https://img1.shopcider.com/product/1659419253000-bTdmp8.jpg?x-oss-process=image/resize,w_350,m_lfit/quality,Q_80/interlace,1"
    ],
    "href": ""
  },
  {
    "productId": 48,
    "price": "13200",
    "brandId": 1,
    "title": "버클 U넥 반팔탑",
    "wishYN": "N",
    "imgUrls": [
      "https://img1.shopcider.com/product/1680947912000-EdNB5z.jpg?x-oss-process=image/resize,w_350,m_lfit/quality,Q_80/interlace,1",
      "https://img1.shopcider.com/product/1680947912000-DWrw2T.jpg?x-oss-process=image/resize,w_350,m_lfit/quality,Q_80/interlace,1"
    ],
    "href": ""
  },
  {
    "productId": 49,
    "price": "26000",
    "brandId": 1,
    "title": "솔리드 미들 웨이스트 플리츠 스커트",
    "wishYN": "N",
    "imgUrls": [
      "https://img1.shopcider.com/product/1672226822000-wKRSMp.jpg?x-oss-process=image/resize,w_350,m_lfit/quality,Q_80/interlace,1",
      "https://img.shopcider.com/hermes/video/1680506294000-7jq6dz.jpg?x-oss-process=image/resize,w_350,m_lfit/quality,Q_80/interlace,1"
    ],
    "href": ""
  },
  {
    "productId": 50,
    "price": "22800",
    "brandId": 1,
    "title": "저지 플라워 그래픽 반팔 탑셔츠",
    "wishYN": "N",
    "imgUrls": [
      "https://img1.shopcider.com/product/1675236673000-8yinH6.jpg?x-oss-process=image/resize,w_350,m_lfit/quality,Q_80/interlace,1",
      "https://img1.shopcider.com/product/1675236673000-JZwbJf.jpg?x-oss-process=image/resize,w_350,m_lfit/quality,Q_80/interlace,1"
    ],
    "href": ""
  },
  {
    "productId": 51,
    "price": "15800",
    "brandId": 1,
    "title": "메쉬 카울넥 크롭 캐미탑",
    "wishYN": "N",
    "imgUrls": [
      "https://img1.shopcider.com/product/1671592312000-jiEfnB.jpg?x-oss-process=image/resize,w_350,m_lfit/quality,Q_80/interlace,1",
      "https://img1.shopcider.com/product/1671592312000-TWxHZA.jpg?x-oss-process=image/resize,w_350,m_lfit/quality,Q_80/interlace,1"
    ],
    "href": ""
  },
  {
    "productId": 52,
    "price": "5300",
    "brandId": 1,
    "title": "지오디자인 후프 이어링",
    "wishYN": "N",
    "imgUrls": [
      "https://img1.shopcider.com/product/1654850709000-rjHC7C.jpg?x-oss-process=image/resize,w_350,m_lfit/quality,Q_80/interlace,1",
      "https://img1.shopcider.com/product/1654850712000-5XAdsE.jpg?x-oss-process=image/resize,w_350,m_lfit/quality,Q_80/interlace,1"
    ],
    "href": ""
  },
  {
    "productId": 53,
    "price": "10500",
    "brandId": 1,
    "title": "솔리드 홀터넥 매듭 캐미 크롭 탑",
    "wishYN": "N",
    "imgUrls": [
      "https://img1.shopcider.com/product/1671287284000-DwfCx6.jpg?x-oss-process=image/resize,w_350,m_lfit/quality,Q_80/interlace,1",
      "https://img1.shopcider.com/product/1671287284000-Yi7hKF.jpg?x-oss-process=image/resize,w_350,m_lfit/quality,Q_80/interlace,1"
    ],
    "href": ""
  },
  {
    "productId": 54,
    "price": "39600",
    "brandId": 1,
    "title": "Miss Crafty 패치워크 데님 미디 스커트",
    "wishYN": "N",
    "imgUrls": [
      "https://img1.shopcider.com/product/1661430337000-KWsGjJ.jpg?x-oss-process=image/resize,w_350,m_lfit/quality,Q_80/interlace,1",
      "https://img.shopcider.com/hermes/video/1674191970000-3rydss.jpg?x-oss-process=image/resize,w_350,m_lfit/quality,Q_80/interlace,1"
    ],
    "href": ""
  },
  {
    "productId": 55,
    "price": "33800",
    "brandId": 1,
    "title": "Ditsy 플로럴 타이 숄더 미니 원피스",
    "wishYN": "N",
    "imgUrls": [
      "https://img1.shopcider.com/product/1654573339000-SphSXT.jpg?x-oss-process=image/resize,w_350,m_lfit/quality,Q_80/interlace,1",
      "https://img1.shopcider.com/product/1654573339000-aeRSX8.jpg?x-oss-process=image/resize,w_350,m_lfit/quality,Q_80/interlace,1"
    ],
    "href": ""
  },
  {
    "productId": 56,
    "price": "26100",
    "brandId": 1,
    "title": "데님 솔리드 하이웨이스트 미니스커트",
    "wishYN": "N",
    "imgUrls": [
      "https://img1.shopcider.com/product/1665975823000-W3cJnJ.jpg?x-oss-process=image/resize,w_350,m_lfit/quality,Q_80/interlace,1",
      "https://img1.shopcider.com/product/1671517731000-hNt4Je.jpg?x-oss-process=image/resize,w_350,m_lfit/quality,Q_80/interlace,1"
    ],
    "href": ""
  },
  {
    "productId": 57,
    "price": "29000",
    "brandId": 1,
    "title": "플리츠 레이스업 미니스커트",
    "wishYN": "N",
    "imgUrls": [
      "https://img1.shopcider.com/product/1680860694000-hFeszx.jpg?x-oss-process=image/resize,w_350,m_lfit/quality,Q_80/interlace,1",
      "https://img1.shopcider.com/product/1680785625000-wPK8ZN.jpg?x-oss-process=image/resize,w_350,m_lfit/quality,Q_80/interlace,1"
    ],
    "href": ""
  },
  {
    "productId": 58,
    "price": "28600",
    "brandId": 1,
    "title": "래빗 니트 크롭 탱크탑",
    "wishYN": "N",
    "imgUrls": [
      "https://img1.shopcider.com/product/1681902980000-QG2Q8W.jpg?x-oss-process=image/resize,w_350,m_lfit/quality,Q_80/interlace,1",
      "https://img1.shopcider.com/product/1679020183000-BjP5BP.jpg?x-oss-process=image/resize,w_350,m_lfit/quality,Q_80/interlace,1"
    ],
    "href": "https://www.shopcider.com/goods/rabbit-knit-crop-tank-top-1033939?style_id=137855&gaListId=-----1&gaListName=%25EC%2583%25B5%25EC%2582%25AC%25EC%259D%25B4%25EB%258B%25A4%2520%25EC%2584%259C%25EC%259A%25B8%2520%25ED%258C%259D%25EC%2597%2585%2520%25EC%258A%25A4%25ED%2586%25A0%25EC%2596%25B4%2520%25EC%25BB%25AC%25EB%25A0%2589%25EC%2585%2598&ciderListId=2&ciderListName=%EC%83%B5%EC%82%AC%EC%9D%B4%EB%8B%A4%20%EC%84%9C%EC%9A%B8%20%ED%8C%9D%EC%97%85%20%EC%8A%A4%ED%86%A0%EC%96%B4%20%EC%BB%AC%EB%A0%89%EC%85%98&selectSkuIndex=0&moduleTitle=1&p=1033939&shopPage=7&shopIndex=123&navTitle=%25EC%2583%25B5%25EC%2582%25AC%25EC%259D%25B4%25EB%258B%25A4%2520%25EC%2584%259C%25EC%259A%25B8%2520%25ED%258C%259D%25EC%2597%2585%2520%25EC%258A%25A4%25ED%2586%25A0%25EC%2596%25B4%2520%25EC%25BB%25AC%25EB%25A0%2589%25EC%2585%2598&navId=-----1&listSort=&listId=11121&listAttribute=&operationContent=&operationImage=&linkUrl=&operationpageTitle=&operationPosition=&operationType=&productPosition=124&strategyNameList=&businessTracking=eyJmaXJzdEltYWdlVHlwZSI6Iuato%2BmdouS4iuWNiui6qyIsIml0ZW1UeXBlIjowLCJsaXN0SWQiOjExMTIxLCJsaXN0VGl0bGUiOiLsg7XsgqzsnbTri6Qg7ISc7Jq4IO2MneyXhSDsiqTthqDslrQg7Lus66CJ7IWYIiwibGlzdFR5cGUiOjIsIm1vZHVsZUlkIjoxLCJwcm9kdWN0UHJpbWFyeUltYWdlRmxhZyI6dHJ1ZSwic2FsZVByaWNlIjoyMy4wMCwic2tjRmlyc3RJbWciOiIxNjgxOTAyOTgwMDAwLVFHMlE4Vy5qcGciLCJzcHUiOjEwMzM5MzksInNwdUNvZGUiOiJDRDIwMjMwMjA4MjQ1MjQ1S1YiLCJ0cmFja2luZ0lkIjoiMTMwNTEyMjg3Nzg0MDE5ODQifQ%3D%3D&listType=2&listTitle=%EC%83%B5%EC%82%AC%EC%9D%B4%EB%8B%A4%20%EC%84%9C%EC%9A%B8%20%ED%8C%9D%EC%97%85%20%EC%8A%A4%ED%86%A0%EC%96%B4%20%EC%BB%AC%EB%A0%89%EC%85%98"
  },
  {
    "productId": 59,
    "price": "28600",
    "brandId": 1,
    "title": "래빗 니트 크롭 탱크탑",
    "wishYN": "N",
    "imgUrls": [
      "https://img1.shopcider.com/product/1681902980000-QG2Q8W.jpg?x-oss-process=image/resize,w_350,m_lfit/quality,Q_80/interlace,1",
      "https://img1.shopcider.com/product/1679020183000-BjP5BP.jpg?x-oss-process=image/resize,w_350,m_lfit/quality,Q_80/interlace,1"
    ],
    "href": "https://www.shopcider.com/goods/rabbit-knit-crop-tank-top-1033939?style_id=137855&gaListId=-----1&gaListName=%25EC%2583%25B5%25EC%2582%25AC%25EC%259D%25B4%25EB%258B%25A4%2520%25EC%2584%259C%25EC%259A%25B8%2520%25ED%258C%259D%25EC%2597%2585%2520%25EC%258A%25A4%25ED%2586%25A0%25EC%2596%25B4%2520%25EC%25BB%25AC%25EB%25A0%2589%25EC%2585%2598&ciderListId=2&ciderListName=%EC%83%B5%EC%82%AC%EC%9D%B4%EB%8B%A4%20%EC%84%9C%EC%9A%B8%20%ED%8C%9D%EC%97%85%20%EC%8A%A4%ED%86%A0%EC%96%B4%20%EC%BB%AC%EB%A0%89%EC%85%98&selectSkuIndex=0&moduleTitle=1&p=1033939&shopPage=7&shopIndex=123&navTitle=%25EC%2583%25B5%25EC%2582%25AC%25EC%259D%25B4%25EB%258B%25A4%2520%25EC%2584%259C%25EC%259A%25B8%2520%25ED%258C%259D%25EC%2597%2585%2520%25EC%258A%25A4%25ED%2586%25A0%25EC%2596%25B4%2520%25EC%25BB%25AC%25EB%25A0%2589%25EC%2585%2598&navId=-----1&listSort=&listId=11121&listAttribute=&operationContent=&operationImage=&linkUrl=&operationpageTitle=&operationPosition=&operationType=&productPosition=124&strategyNameList=&businessTracking=eyJmaXJzdEltYWdlVHlwZSI6Iuato%2BmdouS4iuWNiui6qyIsIml0ZW1UeXBlIjowLCJsaXN0SWQiOjExMTIxLCJsaXN0VGl0bGUiOiLsg7XsgqzsnbTri6Qg7ISc7Jq4IO2MneyXhSDsiqTthqDslrQg7Lus66CJ7IWYIiwibGlzdFR5cGUiOjIsIm1vZHVsZUlkIjoxLCJwcm9kdWN0UHJpbWFyeUltYWdlRmxhZyI6dHJ1ZSwic2FsZVByaWNlIjoyMy4wMCwic2tjRmlyc3RJbWciOiIxNjgxOTAyOTgwMDAwLVFHMlE4Vy5qcGciLCJzcHUiOjEwMzM5MzksInNwdUNvZGUiOiJDRDIwMjMwMjA4MjQ1MjQ1S1YiLCJ0cmFja2luZ0lkIjoiMTMwNTEyMjg3Nzg0MDE5ODQifQ%3D%3D&listType=2&listTitle=%EC%83%B5%EC%82%AC%EC%9D%B4%EB%8B%A4%20%EC%84%9C%EC%9A%B8%20%ED%8C%9D%EC%97%85%20%EC%8A%A4%ED%86%A0%EC%96%B4%20%EC%BB%AC%EB%A0%89%EC%85%98"
  },
  {
    "productId": 60,
    "price": "28600",
    "brandId": 1,
    "title": "래빗 니트 크롭 탱크탑",
    "wishYN": "N",
    "imgUrls": [
      "https://img1.shopcider.com/product/1681902980000-QG2Q8W.jpg?x-oss-process=image/resize,w_350,m_lfit/quality,Q_80/interlace,1",
      "https://img1.shopcider.com/product/1679020183000-BjP5BP.jpg?x-oss-process=image/resize,w_350,m_lfit/quality,Q_80/interlace,1"
    ],
    "href": "https://www.shopcider.com/goods/rabbit-knit-crop-tank-top-1033939?style_id=137855&gaListId=-----1&gaListName=%25EC%2583%25B5%25EC%2582%25AC%25EC%259D%25B4%25EB%258B%25A4%2520%25EC%2584%259C%25EC%259A%25B8%2520%25ED%258C%259D%25EC%2597%2585%2520%25EC%258A%25A4%25ED%2586%25A0%25EC%2596%25B4%2520%25EC%25BB%25AC%25EB%25A0%2589%25EC%2585%2598&ciderListId=2&ciderListName=%EC%83%B5%EC%82%AC%EC%9D%B4%EB%8B%A4%20%EC%84%9C%EC%9A%B8%20%ED%8C%9D%EC%97%85%20%EC%8A%A4%ED%86%A0%EC%96%B4%20%EC%BB%AC%EB%A0%89%EC%85%98&selectSkuIndex=0&moduleTitle=1&p=1033939&shopPage=7&shopIndex=123&navTitle=%25EC%2583%25B5%25EC%2582%25AC%25EC%259D%25B4%25EB%258B%25A4%2520%25EC%2584%259C%25EC%259A%25B8%2520%25ED%258C%259D%25EC%2597%2585%2520%25EC%258A%25A4%25ED%2586%25A0%25EC%2596%25B4%2520%25EC%25BB%25AC%25EB%25A0%2589%25EC%2585%2598&navId=-----1&listSort=&listId=11121&listAttribute=&operationContent=&operationImage=&linkUrl=&operationpageTitle=&operationPosition=&operationType=&productPosition=124&strategyNameList=&businessTracking=eyJmaXJzdEltYWdlVHlwZSI6Iuato%2BmdouS4iuWNiui6qyIsIml0ZW1UeXBlIjowLCJsaXN0SWQiOjExMTIxLCJsaXN0VGl0bGUiOiLsg7XsgqzsnbTri6Qg7ISc7Jq4IO2MneyXhSDsiqTthqDslrQg7Lus66CJ7IWYIiwibGlzdFR5cGUiOjIsIm1vZHVsZUlkIjoxLCJwcm9kdWN0UHJpbWFyeUltYWdlRmxhZyI6dHJ1ZSwic2FsZVByaWNlIjoyMy4wMCwic2tjRmlyc3RJbWciOiIxNjgxOTAyOTgwMDAwLVFHMlE4Vy5qcGciLCJzcHUiOjEwMzM5MzksInNwdUNvZGUiOiJDRDIwMjMwMjA4MjQ1MjQ1S1YiLCJ0cmFja2luZ0lkIjoiMTMwNTEyMjg3Nzg0MDE5ODQifQ%3D%3D&listType=2&listTitle=%EC%83%B5%EC%82%AC%EC%9D%B4%EB%8B%A4%20%EC%84%9C%EC%9A%B8%20%ED%8C%9D%EC%97%85%20%EC%8A%A4%ED%86%A0%EC%96%B4%20%EC%BB%AC%EB%A0%89%EC%85%98"
  },
  {
    "productId": 61,
    "price": "28600",
    "brandId": 1,
    "title": "래빗 니트 크롭 탱크탑",
    "wishYN": "N",
    "imgUrls": [
      "https://img1.shopcider.com/product/1681902980000-QG2Q8W.jpg?x-oss-process=image/resize,w_350,m_lfit/quality,Q_80/interlace,1",
      "https://img1.shopcider.com/product/1679020183000-BjP5BP.jpg?x-oss-process=image/resize,w_350,m_lfit/quality,Q_80/interlace,1"
    ],
    "href": "https://www.shopcider.com/goods/rabbit-knit-crop-tank-top-1033939?style_id=137855&gaListId=-----1&gaListName=%25EC%2583%25B5%25EC%2582%25AC%25EC%259D%25B4%25EB%258B%25A4%2520%25EC%2584%259C%25EC%259A%25B8%2520%25ED%258C%259D%25EC%2597%2585%2520%25EC%258A%25A4%25ED%2586%25A0%25EC%2596%25B4%2520%25EC%25BB%25AC%25EB%25A0%2589%25EC%2585%2598&ciderListId=2&ciderListName=%EC%83%B5%EC%82%AC%EC%9D%B4%EB%8B%A4%20%EC%84%9C%EC%9A%B8%20%ED%8C%9D%EC%97%85%20%EC%8A%A4%ED%86%A0%EC%96%B4%20%EC%BB%AC%EB%A0%89%EC%85%98&selectSkuIndex=0&moduleTitle=1&p=1033939&shopPage=7&shopIndex=123&navTitle=%25EC%2583%25B5%25EC%2582%25AC%25EC%259D%25B4%25EB%258B%25A4%2520%25EC%2584%259C%25EC%259A%25B8%2520%25ED%258C%259D%25EC%2597%2585%2520%25EC%258A%25A4%25ED%2586%25A0%25EC%2596%25B4%2520%25EC%25BB%25AC%25EB%25A0%2589%25EC%2585%2598&navId=-----1&listSort=&listId=11121&listAttribute=&operationContent=&operationImage=&linkUrl=&operationpageTitle=&operationPosition=&operationType=&productPosition=124&strategyNameList=&businessTracking=eyJmaXJzdEltYWdlVHlwZSI6Iuato%2BmdouS4iuWNiui6qyIsIml0ZW1UeXBlIjowLCJsaXN0SWQiOjExMTIxLCJsaXN0VGl0bGUiOiLsg7XsgqzsnbTri6Qg7ISc7Jq4IO2MneyXhSDsiqTthqDslrQg7Lus66CJ7IWYIiwibGlzdFR5cGUiOjIsIm1vZHVsZUlkIjoxLCJwcm9kdWN0UHJpbWFyeUltYWdlRmxhZyI6dHJ1ZSwic2FsZVByaWNlIjoyMy4wMCwic2tjRmlyc3RJbWciOiIxNjgxOTAyOTgwMDAwLVFHMlE4Vy5qcGciLCJzcHUiOjEwMzM5MzksInNwdUNvZGUiOiJDRDIwMjMwMjA4MjQ1MjQ1S1YiLCJ0cmFja2luZ0lkIjoiMTMwNTEyMjg3Nzg0MDE5ODQifQ%3D%3D&listType=2&listTitle=%EC%83%B5%EC%82%AC%EC%9D%B4%EB%8B%A4%20%EC%84%9C%EC%9A%B8%20%ED%8C%9D%EC%97%85%20%EC%8A%A4%ED%86%A0%EC%96%B4%20%EC%BB%AC%EB%A0%89%EC%85%98"
  },
  {
    "productId": 62,
    "price": "28600",
    "brandId": 1,
    "title": "래빗 니트 크롭 탱크탑",
    "wishYN": "N",
    "imgUrls": [
      "https://img1.shopcider.com/product/1681902980000-QG2Q8W.jpg?x-oss-process=image/resize,w_350,m_lfit/quality,Q_80/interlace,1",
      "https://img1.shopcider.com/product/1679020183000-BjP5BP.jpg?x-oss-process=image/resize,w_350,m_lfit/quality,Q_80/interlace,1"
    ],
    "href": "https://www.shopcider.com/goods/rabbit-knit-crop-tank-top-1033939?style_id=137855&gaListId=-----1&gaListName=%25EC%2583%25B5%25EC%2582%25AC%25EC%259D%25B4%25EB%258B%25A4%2520%25EC%2584%259C%25EC%259A%25B8%2520%25ED%258C%259D%25EC%2597%2585%2520%25EC%258A%25A4%25ED%2586%25A0%25EC%2596%25B4%2520%25EC%25BB%25AC%25EB%25A0%2589%25EC%2585%2598&ciderListId=2&ciderListName=%EC%83%B5%EC%82%AC%EC%9D%B4%EB%8B%A4%20%EC%84%9C%EC%9A%B8%20%ED%8C%9D%EC%97%85%20%EC%8A%A4%ED%86%A0%EC%96%B4%20%EC%BB%AC%EB%A0%89%EC%85%98&selectSkuIndex=0&moduleTitle=1&p=1033939&shopPage=7&shopIndex=123&navTitle=%25EC%2583%25B5%25EC%2582%25AC%25EC%259D%25B4%25EB%258B%25A4%2520%25EC%2584%259C%25EC%259A%25B8%2520%25ED%258C%259D%25EC%2597%2585%2520%25EC%258A%25A4%25ED%2586%25A0%25EC%2596%25B4%2520%25EC%25BB%25AC%25EB%25A0%2589%25EC%2585%2598&navId=-----1&listSort=&listId=11121&listAttribute=&operationContent=&operationImage=&linkUrl=&operationpageTitle=&operationPosition=&operationType=&productPosition=124&strategyNameList=&businessTracking=eyJmaXJzdEltYWdlVHlwZSI6Iuato%2BmdouS4iuWNiui6qyIsIml0ZW1UeXBlIjowLCJsaXN0SWQiOjExMTIxLCJsaXN0VGl0bGUiOiLsg7XsgqzsnbTri6Qg7ISc7Jq4IO2MneyXhSDsiqTthqDslrQg7Lus66CJ7IWYIiwibGlzdFR5cGUiOjIsIm1vZHVsZUlkIjoxLCJwcm9kdWN0UHJpbWFyeUltYWdlRmxhZyI6dHJ1ZSwic2FsZVByaWNlIjoyMy4wMCwic2tjRmlyc3RJbWciOiIxNjgxOTAyOTgwMDAwLVFHMlE4Vy5qcGciLCJzcHUiOjEwMzM5MzksInNwdUNvZGUiOiJDRDIwMjMwMjA4MjQ1MjQ1S1YiLCJ0cmFja2luZ0lkIjoiMTMwNTEyMjg3Nzg0MDE5ODQifQ%3D%3D&listType=2&listTitle=%EC%83%B5%EC%82%AC%EC%9D%B4%EB%8B%A4%20%EC%84%9C%EC%9A%B8%20%ED%8C%9D%EC%97%85%20%EC%8A%A4%ED%86%A0%EC%96%B4%20%EC%BB%AC%EB%A0%89%EC%85%98"
  },
  {
    "productId": 63,
    "price": "28600",
    "brandId": 1,

    "title": "래빗 니트 크롭 탱크탑",
    "wishYN": "N",
    "imgUrls": [
      "https://img1.shopcider.com/product/1681902980000-QG2Q8W.jpg?x-oss-process=image/resize,w_350,m_lfit/quality,Q_80/interlace,1",
      "https://img1.shopcider.com/product/1679020183000-BjP5BP.jpg?x-oss-process=image/resize,w_350,m_lfit/quality,Q_80/interlace,1"
    ],
    "href": "https://www.shopcider.com/goods/rabbit-knit-crop-tank-top-1033939?style_id=137855&gaListId=-----1&gaListName=%25EC%2583%25B5%25EC%2582%25AC%25EC%259D%25B4%25EB%258B%25A4%2520%25EC%2584%259C%25EC%259A%25B8%2520%25ED%258C%259D%25EC%2597%2585%2520%25EC%258A%25A4%25ED%2586%25A0%25EC%2596%25B4%2520%25EC%25BB%25AC%25EB%25A0%2589%25EC%2585%2598&ciderListId=2&ciderListName=%EC%83%B5%EC%82%AC%EC%9D%B4%EB%8B%A4%20%EC%84%9C%EC%9A%B8%20%ED%8C%9D%EC%97%85%20%EC%8A%A4%ED%86%A0%EC%96%B4%20%EC%BB%AC%EB%A0%89%EC%85%98&selectSkuIndex=0&moduleTitle=1&p=1033939&shopPage=7&shopIndex=123&navTitle=%25EC%2583%25B5%25EC%2582%25AC%25EC%259D%25B4%25EB%258B%25A4%2520%25EC%2584%259C%25EC%259A%25B8%2520%25ED%258C%259D%25EC%2597%2585%2520%25EC%258A%25A4%25ED%2586%25A0%25EC%2596%25B4%2520%25EC%25BB%25AC%25EB%25A0%2589%25EC%2585%2598&navId=-----1&listSort=&listId=11121&listAttribute=&operationContent=&operationImage=&linkUrl=&operationpageTitle=&operationPosition=&operationType=&productPosition=124&strategyNameList=&businessTracking=eyJmaXJzdEltYWdlVHlwZSI6Iuato%2BmdouS4iuWNiui6qyIsIml0ZW1UeXBlIjowLCJsaXN0SWQiOjExMTIxLCJsaXN0VGl0bGUiOiLsg7XsgqzsnbTri6Qg7ISc7Jq4IO2MneyXhSDsiqTthqDslrQg7Lus66CJ7IWYIiwibGlzdFR5cGUiOjIsIm1vZHVsZUlkIjoxLCJwcm9kdWN0UHJpbWFyeUltYWdlRmxhZyI6dHJ1ZSwic2FsZVByaWNlIjoyMy4wMCwic2tjRmlyc3RJbWciOiIxNjgxOTAyOTgwMDAwLVFHMlE4Vy5qcGciLCJzcHUiOjEwMzM5MzksInNwdUNvZGUiOiJDRDIwMjMwMjA4MjQ1MjQ1S1YiLCJ0cmFja2luZ0lkIjoiMTMwNTEyMjg3Nzg0MDE5ODQifQ%3D%3D&listType=2&listTitle=%EC%83%B5%EC%82%AC%EC%9D%B4%EB%8B%A4%20%EC%84%9C%EC%9A%B8%20%ED%8C%9D%EC%97%85%20%EC%8A%A4%ED%86%A0%EC%96%B4%20%EC%BB%AC%EB%A0%89%EC%85%98"
  }
]
